funcroute/__init__.py
funcroute/cli.py
funcroute/core/__init__.py
funcroute/core/config.py
funcroute/core/router.py
funcroute/data/__init__.py
funcroute/data/formatter.py
funcroute/data/generator.py
funcroute/data/loader.py
funcroute/data/splitter.py
funcroute/data/validator.py
funcroute/evaluation/__init__.py
funcroute/evaluation/evaluator.py
funcroute/evaluation/metrics.py
funcroute/evaluation/visualizer.py
funcroute/inference/__init__.py
funcroute/inference/cache.py
funcroute/inference/predictor.py
funcroute/inference/server.py
funcroute/training/__init__.py
funcroute/training/trainer.py
funcroute-0.1.1.dist-info/licenses/LICENSE
funcroute-0.1.1.dist-info/METADATA
funcroute-0.1.1.dist-info/WHEEL
funcroute-0.1.1.dist-info/entry_points.txt
funcroute-0.1.1.dist-info/top_level.txt
funcroute-0.1.1.dist-info/RECORD
