Metadata-Version: 2.4
Name: funcroute
Version: 0.1.1
Summary: Intelligent function/tool routing using FunctionGemma
Author: Sai Kumar Yava
License: MIT
Project-URL: Homepage, https://github.com/scionoftech/funcroute
Project-URL: Documentation, https://github.com/scionoftech/funcroute/blob/main/README.md
Project-URL: Repository, https://github.com/scionoftech/funcroute
Project-URL: Bug Tracker, https://github.com/scionoftech/funcroute/issues
Keywords: function-calling,tool-routing,functiongemma,agentic-ai,langchain,langgraph,autogen,crewai
Classifier: Development Status :: 3 - Alpha
Classifier: Intended Audience :: Developers
Classifier: Intended Audience :: Science/Research
Classifier: License :: OSI Approved :: MIT License
Classifier: Programming Language :: Python :: 3
Classifier: Programming Language :: Python :: 3.9
Classifier: Programming Language :: Python :: 3.10
Classifier: Programming Language :: Python :: 3.11
Classifier: Programming Language :: Python :: 3.12
Classifier: Topic :: Scientific/Engineering :: Artificial Intelligence
Requires-Python: >=3.9
License-File: LICENSE
Requires-Dist: torch>=2.0.0
Requires-Dist: transformers>=4.36.0
Requires-Dist: peft>=0.7.0
Requires-Dist: trl>=0.7.0
Requires-Dist: accelerate>=0.25.0
Requires-Dist: bitsandbytes>=0.41.0
Requires-Dist: datasets>=2.14.0
Requires-Dist: sentencepiece>=0.1.99
Requires-Dist: pandas>=2.0.0
Requires-Dist: scikit-learn>=1.3.0
Requires-Dist: tqdm>=4.65.0
Requires-Dist: numpy>=1.24.0
Provides-Extra: server
Requires-Dist: fastapi>=0.100.0; extra == "server"
Requires-Dist: uvicorn>=0.23.0; extra == "server"
Provides-Extra: viz
Requires-Dist: matplotlib>=3.7.0; extra == "viz"
Requires-Dist: seaborn>=0.12.0; extra == "viz"
Requires-Dist: wordcloud>=1.9.0; extra == "viz"
Provides-Extra: dev
Requires-Dist: pytest>=7.4.0; extra == "dev"
Requires-Dist: pytest-cov>=4.1.0; extra == "dev"
Requires-Dist: black>=23.0.0; extra == "dev"
Requires-Dist: ruff>=0.1.0; extra == "dev"
Requires-Dist: mypy>=1.5.0; extra == "dev"
Requires-Dist: pre-commit>=3.3.0; extra == "dev"
Provides-Extra: all
Requires-Dist: funcroute[dev,server,viz]; extra == "all"
Dynamic: license-file
